[
null,
{"id":1,"atypeId":1,"description":"Designed for evasion.","etypeId":4,"traits":[{"code":22,"dataId":1,"value":0.2}],"iconIndex":453,"name":"Combat Cloak","note":"","params":[100,0,0,0,0,100,-2,0],"price":1000},
{"id":2,"atypeId":1,"description":"Made for balanced fighting.","etypeId":4,"traits":[],"iconIndex":169,"name":"Leather Vest","note":"","params":[300,0,0,0,0,50,-4,0],"price":1000},
{"id":3,"atypeId":1,"description":"Resist Pull/Push.","etypeId":4,"traits":[],"iconIndex":170,"name":"Plate Mail","note":"","params":[600,0,0,0,0,0,-6,2],"price":1000},
{"id":4,"atypeId":0,"description":"","etypeId":2,"traits":[{"code":22,"dataId":1,"value":0}],"iconIndex":0,"name":"","note":"","params":[0,0,0,0,0,0,0,0],"price":0},
{"id":5,"atypeId":1,"description":"A blade-resistant gauntlet.","etypeId":3,"traits":[{"code":22,"dataId":6,"value":0.2}],"iconIndex":494,"name":"Protector","note":"","params":[100,0,0,0,0,0,-1,0],"price":1000},
{"id":6,"atypeId":1,"description":"Light-weight slashing weapon.","etypeId":3,"traits":[],"iconIndex":385,"name":"Small Dagger","note":"","params":[100,0,0,0,0,0,-1,0],"price":1000},
{"id":7,"atypeId":0,"description":"","etypeId":2,"traits":[{"code":22,"dataId":1,"value":0}],"iconIndex":0,"name":"","note":"","params":[0,0,0,0,0,0,0,0],"price":0},
{"id":8,"atypeId":0,"description":"","etypeId":2,"traits":[{"code":22,"dataId":1,"value":0}],"iconIndex":0,"name":"","note":"","params":[0,0,0,0,0,0,0,0],"price":0},
{"id":9,"atypeId":0,"description":"","etypeId":2,"traits":[{"code":22,"dataId":1,"value":0}],"iconIndex":0,"name":"","note":"","params":[0,0,0,0,0,0,0,0],"price":0},
{"id":10,"atypeId":0,"description":"","etypeId":2,"traits":[{"code":22,"dataId":1,"value":0}],"iconIndex":0,"name":"","note":"","params":[0,0,0,0,0,0,0,0],"price":0},
{"id":11,"atypeId":0,"description":"","etypeId":2,"traits":[{"code":22,"dataId":1,"value":0}],"iconIndex":0,"name":"","note":"","params":[0,0,0,0,0,0,0,0],"price":0},
{"id":12,"atypeId":0,"description":"","etypeId":2,"traits":[{"code":22,"dataId":1,"value":0}],"iconIndex":0,"name":"","note":"","params":[0,0,0,0,0,0,0,0],"price":0},
{"id":13,"atypeId":0,"description":"","etypeId":2,"traits":[{"code":22,"dataId":1,"value":0}],"iconIndex":0,"name":"","note":"","params":[0,0,0,0,0,0,0,0],"price":0},
{"id":14,"atypeId":0,"description":"","etypeId":2,"traits":[{"code":22,"dataId":1,"value":0}],"iconIndex":0,"name":"","note":"","params":[0,0,0,0,0,0,0,0],"price":0},
{"id":15,"atypeId":0,"description":"","etypeId":2,"traits":[{"code":22,"dataId":1,"value":0}],"iconIndex":0,"name":"","note":"","params":[0,0,0,0,0,0,0,0],"price":0},
{"id":16,"atypeId":0,"description":"","etypeId":2,"traits":[{"code":22,"dataId":1,"value":0}],"iconIndex":0,"name":"","note":"","params":[0,0,0,0,0,0,0,0],"price":0},
{"id":17,"atypeId":0,"description":"","etypeId":2,"traits":[{"code":22,"dataId":1,"value":0}],"iconIndex":0,"name":"","note":"","params":[0,0,0,0,0,0,0,0],"price":0},
{"id":18,"atypeId":0,"description":"","etypeId":2,"traits":[{"code":22,"dataId":1,"value":0}],"iconIndex":0,"name":"","note":"","params":[0,0,0,0,0,0,0,0],"price":0},
{"id":19,"atypeId":0,"description":"","etypeId":2,"traits":[{"code":22,"dataId":1,"value":0}],"iconIndex":0,"name":"","note":"","params":[0,0,0,0,0,0,0,0],"price":0},
{"id":20,"atypeId":0,"description":"","etypeId":2,"traits":[],"iconIndex":0,"name":"","note":"","params":[0,0,0,0,0,0,0,0],"price":0},
{"id":21,"atypeId":0,"description":"","etypeId":2,"traits":[{"code":22,"dataId":1,"value":0}],"iconIndex":0,"name":"","note":"","params":[0,0,0,0,0,0,0,0],"price":0},
{"id":22,"atypeId":0,"description":"","etypeId":2,"traits":[{"code":22,"dataId":1,"value":0}],"iconIndex":0,"name":"","note":"","params":[0,0,0,0,0,0,0,0],"price":0},
{"id":23,"atypeId":0,"description":"","etypeId":2,"traits":[{"code":22,"dataId":1,"value":0}],"iconIndex":0,"name":"","note":"","params":[0,0,0,0,0,0,0,0],"price":0},
{"id":24,"atypeId":0,"description":"","etypeId":2,"traits":[{"code":22,"dataId":1,"value":0}],"iconIndex":0,"name":"","note":"","params":[0,0,0,0,0,0,0,0],"price":0},
{"id":25,"atypeId":0,"description":"","etypeId":2,"traits":[{"code":22,"dataId":1,"value":0}],"iconIndex":0,"name":"","note":"","params":[0,0,0,0,0,0,0,0],"price":0},
{"id":26,"atypeId":0,"description":"","etypeId":2,"traits":[{"code":22,"dataId":1,"value":0}],"iconIndex":0,"name":"","note":"","params":[0,0,0,0,0,0,0,0],"price":0},
{"id":27,"atypeId":0,"description":"","etypeId":2,"traits":[{"code":22,"dataId":1,"value":0}],"iconIndex":0,"name":"","note":"","params":[0,0,0,0,0,0,0,0],"price":0},
{"id":28,"atypeId":0,"description":"","etypeId":2,"traits":[{"code":22,"dataId":1,"value":0}],"iconIndex":0,"name":"","note":"","params":[0,0,0,0,0,0,0,0],"price":0},
{"id":29,"atypeId":0,"description":"","etypeId":2,"traits":[{"code":22,"dataId":1,"value":0}],"iconIndex":0,"name":"","note":"","params":[0,0,0,0,0,0,0,0],"price":0},
{"id":30,"atypeId":0,"description":"","etypeId":2,"traits":[{"code":22,"dataId":1,"value":0}],"iconIndex":0,"name":"","note":"","params":[0,0,0,0,0,0,0,0],"price":0},
{"id":31,"atypeId":0,"description":"","etypeId":2,"traits":[{"code":22,"dataId":1,"value":0}],"iconIndex":0,"name":"","note":"","params":[0,0,0,0,0,0,0,0],"price":0},
{"id":32,"atypeId":0,"description":"","etypeId":2,"traits":[{"code":22,"dataId":1,"value":0}],"iconIndex":0,"name":"","note":"","params":[0,0,0,0,0,0,0,0],"price":0},
{"id":33,"atypeId":0,"description":"","etypeId":2,"traits":[{"code":22,"dataId":1,"value":0}],"iconIndex":0,"name":"","note":"","params":[0,0,0,0,0,0,0,0],"price":0},
{"id":34,"atypeId":0,"description":"","etypeId":2,"traits":[{"code":22,"dataId":1,"value":0}],"iconIndex":0,"name":"","note":"","params":[0,0,0,0,0,0,0,0],"price":0},
{"id":35,"atypeId":0,"description":"","etypeId":2,"traits":[{"code":22,"dataId":1,"value":0}],"iconIndex":0,"name":"","note":"","params":[0,0,0,0,0,0,0,0],"price":0},
{"id":36,"atypeId":0,"description":"","etypeId":2,"traits":[{"code":22,"dataId":1,"value":0}],"iconIndex":0,"name":"","note":"","params":[0,0,0,0,0,0,0,0],"price":0},
{"id":37,"atypeId":0,"description":"","etypeId":2,"traits":[{"code":22,"dataId":1,"value":0}],"iconIndex":0,"name":"","note":"","params":[0,0,0,0,0,0,0,0],"price":0},
{"id":38,"atypeId":0,"description":"","etypeId":2,"traits":[{"code":22,"dataId":1,"value":0}],"iconIndex":0,"name":"","note":"","params":[0,0,0,0,0,0,0,0],"price":0},
{"id":39,"atypeId":0,"description":"","etypeId":2,"traits":[{"code":22,"dataId":1,"value":0}],"iconIndex":0,"name":"","note":"","params":[0,0,0,0,0,0,0,0],"price":0},
{"id":40,"atypeId":0,"description":"","etypeId":2,"traits":[{"code":22,"dataId":1,"value":0}],"iconIndex":0,"name":"","note":"","params":[0,0,0,0,0,0,0,0],"price":0}
]